{"chunk_id": "naver::7975172::c0", "doc_id": "naver::7975172", "chunk_idx": 0, "source": "naver_cafe", "url": "http://cafe.naver.com/starbucksrent/777", "fetched_at": "2026-02-04T15:12:57", "title": "스타벅스 하버타운점 | 스타벅스 해운대구 하버타운점 – 해운대 바다를 품은 오션뷰 감성 카페", "text": "가게명: 스타벅스 하버타운점 | 주소: 부산 해운대구 해운대해변로 257 | 지역: 해운대구 | 근거요약: \" 요약 스타벅스 해운대구 하버타운점은 해운대 바다를 한눈에 담을 수 있는 오션뷰, 넉넉한 좌석과 주차, 다양한 메뉴와 굿즈, 밝고 쾌적한 분위기, 친절한 서비스까지 모두 누릴 수 있는 해운대 대표 감성 카페입니다....", "shop": "스타벅스 하버타운점", "address": "부산 해운대구 해운대해변로 257", "area_gu": "해운대구", "area_dong": "", "evidence": {"title": "스타벅스 해운대구 하버타운점 – 해운대 바다를 품은 오션뷰 감성 카페", "description": "\" 요약 스타벅스 해운대구 하버타운점은 해운대 바다를 한눈에 담을 수 있는 오션뷰, 넉넉한 좌석과 주차, 다양한 메뉴와 굿즈, 밝고 쾌적한 분위기, 친절한 서비스까지 모두 누릴 수 있는 해운대 대표 감성 카페입니다....", "snippet": "\" 요약 스타벅스 해운대구 하버타운점은 해운대 바다를 한눈에 담을 수 있는 오션뷰, 넉넉한 좌석과 주차, 다양한 메뉴와 굿즈, 밝고 쾌적한 분위기, 친절한 서비스까지 모두 누릴 수 있는 해운대 대표 감성 카페입니다....", "link": "http://cafe.naver.com/starbucksrent/777"}, "evi_score": 0.815, "evi_feats": {"len": 162, "len_score": 0.675, "kw_hits": 3, "kw_score": 0.75, "exp_hits": 7, "exp_score": 1.0, "ban_hits": 0, "ad_penalty": 0.0, "hashtag_cnt": 0, "tag_penalty": 0.0, "list_penalty": 0.0}, "evi_gate_reason": "ok"}