{"chunk_id": "naver::1719097739::c0", "doc_id": "naver::1719097739", "chunk_idx": 0, "source": "naver_cafe", "url": "http://cafe.naver.com/pusandamoim/14175", "fetched_at": "2026-02-04T15:16:29", "title": "메츠 과자점 본점 | 어떤 빵을 제일 좋아하시나요", "text": "가게명: 메츠 과자점 본점 | 주소: 부산 남구 수영로266번길 46 | 지역: 남구 | 근거요약: 다음은 부산 남구에 있는 빵집들이에요. 이흥용과자점 문현직영점, 겐츠베이커리 본점, 롤뺑드빠리, 보타닉아덴, 구월의마카롱, 브레드 365, 아델라7 대연점, 수수베이커리, 파리바게뜨 경성대점, 메츠과자점...", "shop": "메츠 과자점 본점", "address": "부산 남구 수영로266번길 46", "area_gu": "남구", "area_dong": "", "evidence": {"title": "어떤 빵을 제일 좋아하시나요", "description": "다음은 부산 남구에 있는 빵집들이에요. 이흥용과자점 문현직영점, 겐츠베이커리 본점, 롤뺑드빠리, 보타닉아덴, 구월의마카롱, 브레드 365, 아델라7 대연점, 수수베이커리, 파리바게뜨 경성대점, 메츠과자점...", "snippet": "다음은 부산 남구에 있는 빵집들이에요. 이흥용과자점 문현직영점, 겐츠베이커리 본점, 롤뺑드빠리, 보타닉아덴, 구월의마카롱, 브레드 365, 아델라7 대연점, 수수베이커리, 파리바게뜨 경성대점, 메츠과자점...", "link": "http://cafe.naver.com/pusandamoim/14175"}, "evi_score": 0.5733333333333333, "evi_feats": {"len": 132, "len_score": 0.55, "kw_hits": 2, "kw_score": 0.5, "exp_hits": 2, "exp_score": 0.6666666666666666, "ban_hits": 0, "ad_penalty": 0.0, "hashtag_cnt": 0, "tag_penalty": 0.0, "list_penalty": 0.0}, "evi_gate_reason": "ok"}