{"chunk_id": "naver::8117017::c0", "doc_id": "naver::8117017", "chunk_idx": 0, "source": "naver_cafe", "url": "http://cafe.naver.com/bk1009/3744384", "fetched_at": "2026-02-04T15:23:28", "title": "파리바게뜨 동래내성점 | 부산) 연산동 코오롱하늘채 분양가 부산아파트분양 정보 알아봅시다.", "text": "가게명: 파리바게뜨 동래내성점 | 주소: 부산 동래구 충렬대로 157 | 지역: 동래구 | 근거요약: 42번버스, 49번버스, 54번버스, 57번버스, 87번버스, 210번버스 금정구 동래구 부산진구 수영구 부산남구... 토곡맛집파리바게뜨 연산동맛있는빵집 옵스 토곡숨은맛집 초등학교 중학교 고등학교 대학교골프동호회...", "shop": "파리바게뜨 동래내성점", "address": "부산 동래구 충렬대로 157", "area_gu": "동래구", "area_dong": "", "evidence": {"title": "부산) 연산동 코오롱하늘채 분양가 부산아파트분양 정보 알아봅시다.", "description": "42번버스, 49번버스, 54번버스, 57번버스, 87번버스, 210번버스 금정구 동래구 부산진구 수영구 부산남구... 토곡맛집파리바게뜨 연산동맛있는빵집 옵스 토곡숨은맛집 초등학교 중학교 고등학교 대학교골프동호회...", "snippet": "42번버스, 49번버스, 54번버스, 57번버스, 87번버스, 210번버스 금정구 동래구 부산진구 수영구 부산남구... 토곡맛집파리바게뜨 연산동맛있는빵집 옵스 토곡숨은맛집 초등학교 중학교 고등학교 대학교골프동호회...", "link": "http://cafe.naver.com/bk1009/3744384"}, "evi_score": 0.6058333333333332, "evi_feats": {"len": 158, "len_score": 0.6583333333333333, "kw_hits": 2, "kw_score": 0.5, "exp_hits": 2, "exp_score": 0.6666666666666666, "ban_hits": 0, "ad_penalty": 0.0, "hashtag_cnt": 0, "tag_penalty": 0.0, "list_penalty": 0.0}, "evi_gate_reason": "ok"}