{"chunk_id": "naver::625367644::c0", "doc_id": "naver::625367644", "chunk_idx": 0, "source": "naver_cafe", "url": "http://cafe.naver.com/ddwumiceambassador/543", "fetched_at": "2026-02-04T15:27:10", "title": "뮤직컴플렉스서울 부산점 | [개인미션] MICE 최신 이슈 스크랩", "text": "가게명: 뮤직컴플렉스서울 부산점 | 주소: 부산 기장군 기장읍 동부산관광로 34 | 지역: 기장군 | 근거요약: (부산진구) △뮤직컴플렉스서울 부산점(기장군) △부산근현대역사관(중구) △부산영화체험박물관(중구) △스페이스 별일(부산진구) △스페이스 원지(영도구) △태종대 오션플라잉 테마파크(영도구) △해운대플랫폼...", "shop": "뮤직컴플렉스서울 부산점", "address": "부산 기장군 기장읍 동부산관광로 34", "area_gu": "기장군", "area_dong": "", "evidence": {"title": "[개인미션] MICE 최신 이슈 스크랩", "description": "(부산진구) △뮤직컴플렉스서울 부산점(기장군) △부산근현대역사관(중구) △부산영화체험박물관(중구) △스페이스 별일(부산진구) △스페이스 원지(영도구) △태종대 오션플라잉 테마파크(영도구) △해운대플랫폼...", "snippet": "(부산진구) △뮤직컴플렉스서울 부산점(기장군) △부산근현대역사관(중구) △부산영화체험박물관(중구) △스페이스 별일(부산진구) △스페이스 원지(영도구) △태종대 오션플라잉 테마파크(영도구) △해운대플랫폼...", "link": "http://cafe.naver.com/ddwumiceambassador/543"}, "evi_score": 0.5504166666666667, "evi_feats": {"len": 137, "len_score": 0.5708333333333333, "kw_hits": 3, "kw_score": 0.75, "exp_hits": 1, "exp_score": 0.3333333333333333, "ban_hits": 0, "ad_penalty": 0.0, "hashtag_cnt": 0, "tag_penalty": 0.0, "list_penalty": 0.0}, "evi_gate_reason": "ok"}