{"chunk_id": "naver::846411755::c0", "doc_id": "naver::846411755", "chunk_idx": 0, "source": "naver_cafe", "url": "http://cafe.naver.com/wecando7/4818729", "fetched_at": "2026-02-04T15:15:47", "title": "스타벅스 금련산역점 | [실준26기 6캔두잇불4조 내세꼭] 1주차 과제, 부산시 연제구 분위기 임장 후기", "text": "가게명: 스타벅스 금련산역점 | 주소: 부산 수영구 수영로464번길 6 | 지역: 수영구 | 근거요약: 북구, 수영구, 금정구, 사하구는 사하역정도까지) + 거의 김해시청까지 거제센트럴자이아파트... 주변 환경 ㅇ 스타벅스가 있고 길을 건너면 망미중앙시장이 있다 ㅇ 길 건너 상권이 잘 발달되어있다 5. 임장후 느낌 ㅇ...", "shop": "스타벅스 금련산역점", "address": "부산 수영구 수영로464번길 6", "area_gu": "수영구", "area_dong": "", "evidence": {"title": "[실준26기 6캔두잇불4조 내세꼭] 1주차 과제, 부산시 연제구 분위기 임장 후기", "description": "북구, 수영구, 금정구, 사하구는 사하역정도까지) + 거의 김해시청까지 거제센트럴자이아파트... 주변 환경 ㅇ 스타벅스가 있고 길을 건너면 망미중앙시장이 있다 ㅇ 길 건너 상권이 잘 발달되어있다 5. 임장후 느낌 ㅇ...", "snippet": "북구, 수영구, 금정구, 사하구는 사하역정도까지) + 거의 김해시청까지 거제센트럴자이아파트... 주변 환경 ㅇ 스타벅스가 있고 길을 건너면 망미중앙시장이 있다 ㅇ 길 건너 상권이 잘 발달되어있다 5. 임장후 느낌 ㅇ...", "link": "http://cafe.naver.com/wecando7/4818729"}, "evi_score": 0.7070833333333333, "evi_feats": {"len": 169, "len_score": 0.7041666666666667, "kw_hits": 3, "kw_score": 0.75, "exp_hits": 2, "exp_score": 0.6666666666666666, "ban_hits": 0, "ad_penalty": 0.0, "hashtag_cnt": 0, "tag_penalty": 0.0, "list_penalty": 0.0}, "evi_gate_reason": "ok"}