{
  "id": "naver_blog_003ed60ea698ef7f2c803b77932559b7b23952ae",
  "meta": {
    "source": "naver_blog",
    "url": "https://blog.naver.com/eunji318/223606448035",
    "title": "부산 광안리 오션뷰 카페 추천 비엔나커피",
    "query": "부산 광안리 카페",
    "fetched_at": "2026-01-28T12:57:18",
    "ok": true
  },
  "text": "부산 광안리 오션뷰 카페 추천 비엔나커피\n- 요약: 가세요 (광안리 주차장 주차료가 진짜 부산에서 젤 비싼 듯 ㅠㅠㅠ 꼭 챙기셔야 합니다 ㅎㅎ) 날씨가 선선해져서 카페 데이트하기 참 좋은 날씨예요. 친구와, 가족과, 연인과 함께 가기 좋은 부산 광안리 카페...\n- 링크: https://blog.naver.com/eunji318/223606448035\n- 키워드: 부산 광안리 카페"
}