{
  "id": "naver_blog_034aca450b6d7e5ee2526ef2ade3caf839c9c689",
  "meta": {
    "source": "naver_blog",
    "url": "https://blog.naver.com/spaceworkshop/223467547894",
    "title": "망미단길) 주택개조 카페 빵도 커피도 맛있습니다!! 부산...",
    "query": "부산 망미단길 카페 조용한카페 작업하기",
    "fetched_at": "2026-01-28T13:22:19",
    "ok": true
  },
  "text": "망미단길) 주택개조 카페 빵도 커피도 맛있습니다!! 부산...\n- 요약: 전기작업 추가로 커피바의 전체 치수와 이에 맞는 최적의 동선을 여러 번 체크한 뒤에 커피바를... @ 부산 공간공작소 인테리어 문의 010-****-**** #부산인테리어 #망미단길 #망미동카페 #베이커리카페...\n- 링크: https://blog.naver.com/spaceworkshop/223467547894\n- 키워드: 부산 망미단길 카페 조용한카페 작업하기"
}