{
  "id": "naver_blog_06e350fd8b1312e9e02f6fc21f740ac1a2ff097b",
  "meta": {
    "source": "naver_blog",
    "url": "https://blog.naver.com/xxyxnxa/224092330552",
    "title": "부산 해리단길 빵집 추천 반지하 베이커리 해운대 밀창고",
    "query": "부산 해리단길 카페 대형카페 베이커리",
    "fetched_at": "2026-01-28T13:20:17",
    "ok": true
  },
  "text": "부산 해리단길 빵집 추천 반지하 베이커리 해운대 밀창고\n- 요약: 조용하고 아늑한 무드의 베이커리 카페에서 힐링하고 싶은 빵순이, 빵돌이들 주목 지난 여름 친구랑 부산에 놀러갔다가 해운대 해리단길 베이커리 카페 밀창고에 다녀왔어요. 둘 다 빵 취향이 비슷해서...\n- 링크: https://blog.naver.com/xxyxnxa/224092330552\n- 키워드: 부산 해리단길 카페 대형카페 베이커리"
}