{
  "id": "naver_blog_1106acb8f36bd5197090ff2bd61b4dcfdad83801",
  "meta": {
    "source": "naver_blog",
    "url": "https://blog.naver.com/ddoyoung5/224024993484",
    "title": "부산 광안리 신상 카페 데이오프데이 무화과 디저트 맛집",
    "query": "부산 광안리 디저트 카페",
    "fetched_at": "2026-01-28T13:05:02",
    "ok": true
  },
  "text": "부산 광안리 신상 카페 데이오프데이 무화과 디저트 맛집\n- 요약: 부산 광안리 신상 카페, 무화과 디저트 맛집으로 유명한 데이오프데이 광안점을 영상으로도 만나보세요! 위치 평소에 무화과 디저트를 좋아하신다면 부산 광안리에 새로 생긴 신상 카페, 데이오프데이에서...\n- 링크: https://blog.naver.com/ddoyoung5/224024993484\n- 키워드: 부산 광안리 디저트 카페"
}