{
  "id": "naver_blog_156a348c98edb131638f9fbbe56a7e850a7a2c5e",
  "meta": {
    "source": "naver_blog",
    "url": "https://blog.naver.com/ryung1105/223268332710",
    "title": "부산 강서구 대형 베이커리 카페 명지 큐씨카페 QC",
    "query": "부산 명지 카페 대형카페 베이커리",
    "fetched_at": "2026-01-28T13:19:04",
    "ok": true
  },
  "text": "부산 강서구 대형 베이커리 카페 명지 큐씨카페 QC\n- 요약: 안에들어갔을때도 대형카페 답게 화려화구만요! 자, 일단 엄마랑 빵 부터골라보도록할까요~? 점심때쯤 갓을때였는데 빵종류가 생각보다 빠진것들이 많았어요 선택의 폭이 넓은 부산 명지 강서구 베이커리 카페...\n- 링크: https://blog.naver.com/ryung1105/223268332710\n- 키워드: 부산 명지 카페 대형카페 베이커리"
}