{
  "id": "naver_blog_15b37fb68749c2bd0147ae53ee3909e76007d4f8",
  "meta": {
    "source": "naver_blog",
    "url": "https://blog.naver.com/qkrxjvm7548/223620572186",
    "title": "부산 괴정 모래놀이 카페 시온 아이랑 신나게 놀다오기",
    "query": "부산 괴정 카페",
    "fetched_at": "2026-01-28T13:17:44",
    "ok": true
  },
  "text": "부산 괴정 모래놀이 카페 시온 아이랑 신나게 놀다오기\n- 요약: 부산 카페 시온 / 괴정 카페 시온 부산 모래놀이 카페 여기 좋아! 부산 아이랑 카페 :) 사진.글 © 로니로이 지난 주말 부산 나들이를 갔다가 숙박을 하고 돌아오는 길, 어디를 가볼까? 했는데 월요일이라 오픈한...\n- 링크: https://blog.naver.com/qkrxjvm7548/223620572186\n- 키워드: 부산 괴정 카페"
}