{
  "id": "naver_blog_15c427b30594e66b8bebfb77fce3a83a582ea66b",
  "meta": {
    "source": "naver_blog",
    "url": "https://blog.naver.com/toffezip/223549968236",
    "title": "영도 흰여울문화마을 오션뷰 카페 리스보아 솔직후기",
    "query": "부산 구서동 카페 뷰카페 오션뷰",
    "fetched_at": "2026-01-28T13:21:07",
    "ok": true
  },
  "text": "영도 흰여울문화마을 오션뷰 카페 리스보아 솔직후기\n- 요약: 뷰를 보고 싶으시다면 2층에 앉으시길 :) #영도카페 #흰여울문화마을카페 #리스보아영도 #영도흰여울문화마을 #부산영도가볼만한곳 #영도뷰카페 #영도오션뷰카페 #리스보아 #서이추 #서이추환영\n- 링크: https://blog.naver.com/toffezip/223549968236\n- 키워드: 부산 구서동 카페 뷰카페 오션뷰"
}