{
  "id": "naver_blog_1c881238f80478b835485eb9350ac318e93cbb61",
  "meta": {
    "source": "naver_blog",
    "url": "https://blog.naver.com/brisbane8/223798453343",
    "title": "해운대카페추천 피스타치오 음료 맛집 갈바트카페 부산해운대...",
    "query": "부산 해운대 카페",
    "fetched_at": "2026-01-28T13:14:31",
    "ok": true
  },
  "text": "해운대카페추천 피스타치오 음료 맛집 갈바트카페 부산해운대...\n- 요약: 안녕하세요 빌리브정입니다 :) 풍부한 원재료를 사용하면서 매일 마셔도 부담없는 가격으로 찾을 수 있는 해운대가볼만한곳 해운대카페추천 갈바트카페 부산해운대캐슬점 소개시켜드릴게요...\n- 링크: https://blog.naver.com/brisbane8/223798453343\n- 키워드: 부산 해운대 카페"
}