{
  "id": "naver_blog_1ccb2afce5efa33931a8532c39896dfc097ce855",
  "meta": {
    "source": "naver_blog",
    "url": "https://blog.naver.com/gilu333/223868471845",
    "title": "부산남구디저트 카페 문현동 팥꽃피다 국내산 팥빙수 맛집",
    "query": "부산 문현동 카페 대형카페 베이커리",
    "fetched_at": "2026-01-28T13:19:16",
    "ok": true
  },
  "text": "부산남구디저트 카페 문현동 팥꽃피다 국내산 팥빙수 맛집\n- 요약: 부산남구 베이커리카페 팥죽도 있네! 문현동 팥빙수 맛집 전포동이 핫해지면서 점차 숨겨져 있던 문현동이 주목을 받기 시작했는데요. 저는 이미 8년 전부터 이곳이 유명해질 거라 예상했는데 드문드문 괜찮은...\n- 링크: https://blog.naver.com/gilu333/223868471845\n- 키워드: 부산 문현동 카페 대형카페 베이커리"
}