{
  "id": "naver_blog_1f0eb9ade308a1fb14bc6a660eff515fa431dbf7",
  "meta": {
    "source": "naver_blog",
    "url": "https://blog.naver.com/h_j_bom/223515227447",
    "title": "부산 사하 맛집 [ 젬스톤 ] 베이커리 카페 추천",
    "query": "부산 사하 카페 대형카페 베이커리",
    "fetched_at": "2026-01-28T13:21:09",
    "ok": true
  },
  "text": "부산 사하 맛집 [ 젬스톤 ] 베이커리 카페 추천\n- 요약: 영도에 뷰가 좋은 모 대형카페는 테이블이 너무 많아서 손님들끼리 밀집도가 높아 불편하고 정신없는... 베이커리며 음료며 분위기까지 좋은 부산 카페 추천 사하구 인근이면 꼭 방문해보길! 이이글 은은체 험...\n- 링크: https://blog.naver.com/h_j_bom/223515227447\n- 키워드: 부산 사하 카페 대형카페 베이커리"
}