{
  "id": "naver_blog_220907723bed83aa76ac81fd7b5f561819dee054",
  "meta": {
    "source": "naver_blog",
    "url": "https://blog.naver.com/song_manager/224141427896",
    "title": "부산 전포 카페 디저트 맛집 어퍼이스트베이커리 선물포장",
    "query": "부산 전포 카페",
    "fetched_at": "2026-01-28T13:08:32",
    "ok": true
  },
  "text": "부산 전포 카페 디저트 맛집 어퍼이스트베이커리 선물포장\n- 요약: ▼함께 보면 좋은 글▼ 촬영기기 : Sony A7C2 + 2470gm2 photographed by 맛집사원 송매니저 contact : ************@naver.com #부산카페 #부산전포카페디저트맛집어퍼이스트베이커리포장후기 #전포카페 #부산전포디저트...\n- 링크: https://blog.naver.com/song_manager/224141427896\n- 키워드: 부산 전포 카페"
}