{
  "id": "naver_blog_280774b66786316522a0371eff6b82564cf455d0",
  "meta": {
    "source": "naver_blog",
    "url": "https://blog.naver.com/dreat-/223679789010",
    "title": "부산 광안리 카페 커피 디저트 맛집 뚜벅스 오션뷰 드론쇼 명당",
    "query": "부산 광안리 카페",
    "fetched_at": "2026-01-28T12:57:22",
    "ok": true
  },
  "text": "부산 광안리 카페 커피 디저트 맛집 뚜벅스 오션뷰 드론쇼 명당\n- 요약: 부산 여행에서 빠질 수 없는 광안리 해수욕장. 뷰가 멋진 뚜벅스 카페 다녀왔어요. 광안리 카페 뷰 좋은 곳을 찾으신다면 추천합니다. 음료&amp;디저트도 맛있어요. 저녁에는 칵테일, 맥주 등 가볍게 한잔하기에도...\n- 링크: https://blog.naver.com/dreat-/223679789010\n- 키워드: 부산 광안리 카페"
}