{
  "id": "naver_blog_297e12cf3a9a64625e8c9acc41e98f36bd06a627",
  "meta": {
    "source": "naver_blog",
    "url": "https://blog.naver.com/carpediem1980/224147666868",
    "title": "부산 광안리 오션뷰 전망 좋은 카페",
    "query": "부산 광안리 카페",
    "fetched_at": "2026-01-28T12:57:08",
    "ok": true
  },
  "text": "부산 광안리 오션뷰 전망 좋은 카페\n- 요약: 음료도 맛있구. 살짝 시장통같긴 하지만 ㅋㅋ 부산 광안리 오션뷰 전망좋은 카페를 찾고 계셨다면 여기 리코리카 추천해드림. 부산 여행 준비중 이시라면 아래 링크 추천해드림. https://m.site.naver.com/1YLm6\n- 링크: https://blog.naver.com/carpediem1980/224147666868\n- 키워드: 부산 광안리 카페"
}