{
  "id": "naver_blog_2b9afccfdbe42b0bfba75195c716a67249524170",
  "meta": {
    "source": "naver_blog",
    "url": "https://blog.naver.com/love_juu/223299028977",
    "title": "크리스마스 케이크 부산 서면 카페 힌터크룬트 전포에서 예약주문",
    "query": "부산 서면 카페",
    "fetched_at": "2026-01-28T13:12:37",
    "ok": true
  },
  "text": "크리스마스 케이크 부산 서면 카페 힌터크룬트 전포에서 예약주문\n- 요약: 위해 부산 서면 카페 힌터그룬트 전포에서 크리스마스 케이크를 예약 주문했답니다. 부산 케이크 맛집 서면 카페 힌터그룬트는 지하철 2호선 전포역 2번과 4번출구에서 도보 3분 거리에 위치해 있어요....\n- 링크: https://blog.naver.com/love_juu/223299028977\n- 키워드: 부산 서면 카페"
}