{
  "id": "naver_blog_2c71ee5f2de6e7ce0fe91ace2fd672f1e2388ca6",
  "meta": {
    "source": "naver_blog",
    "url": "https://blog.naver.com/fls7488/224085854218",
    "title": "부산 광안리 근처 카페, 일기장ㅣ휘낭시에 맛있는 남천동 커피",
    "query": "부산 광안리 카페",
    "fetched_at": "2026-01-28T12:57:27",
    "ok": true
  },
  "text": "부산 광안리 근처 카페, 일기장ㅣ휘낭시에 맛있는 남천동 커피\n- 요약: 0507-1337-4794 부산 광안리 근처 카페, 일기장 원래 일기장 카페가 함안에 있다가 부산으로 이전하셨는데, 함안에 있을 때부터 가고 싶어서 저장해둔 카페에요 그런데 부산으로 이전해서 부산으로 방문했어요!...\n- 링크: https://blog.naver.com/fls7488/224085854218\n- 키워드: 부산 광안리 카페"
}