{
  "id": "naver_blog_33fe8d7cabb36676f3a6a97807af0db188c86eda",
  "meta": {
    "source": "naver_blog",
    "url": "https://blog.naver.com/loun0202/224133411554",
    "title": "부산 광안리 카페 샌디스, 뷰 맛집 디저트 맛집 데이트코스 카페...",
    "query": "부산 광안리 디저트 카페",
    "fetched_at": "2026-01-28T13:04:36",
    "ok": true
  },
  "text": "부산 광안리 카페 샌디스, 뷰 맛집 디저트 맛집 데이트코스 카페...\n- 요약: 부산 광안리 카페 샌디스 총평 디저트가 맛있고 뷰가 환상적이었던 유명한 카페 샌디스! 광안리에 놀러가신다면 꼭 한 번은 방문해보셨으면 하는 카페예요! 다음에는 꼭 일찍 방문해서 딸기 파블로바를...\n- 링크: https://blog.naver.com/loun0202/224133411554\n- 키워드: 부산 광안리 디저트 카페"
}