{
  "id": "naver_blog_391d83b1e88d8d743ee6541f5193161b7bf0e247",
  "meta": {
    "source": "naver_blog",
    "url": "https://blog.naver.com/binsandjia/224109027173",
    "title": "부산 대형 베이커리 카페 가원, 드디어 다녀왔어요!",
    "query": "부산 문현동 카페 대형카페 베이커리",
    "fetched_at": "2026-01-28T13:19:22",
    "ok": true
  },
  "text": "부산 대형 베이커리 카페 가원, 드디어 다녀왔어요!\n- 요약: #부산가원 #가원 #부산대형카페 #부산베이커리카페 #부산베이커리맛집 #부산빵집 #부산카페추천 #부산가볼만한곳 #주말나들이 #가족나들이 #아이와가기좋은곳 #부산데이트코스 #부산데이트 #인생샷카페...\n- 링크: https://blog.naver.com/binsandjia/224109027173\n- 키워드: 부산 문현동 카페 대형카페 베이커리"
}