{
  "id": "naver_blog_3ccbc911e9bfb6e8c26d8d2902ed4370813f4205",
  "meta": {
    "source": "naver_blog",
    "url": "https://blog.naver.com/mini11_/224103220010",
    "title": "부산 전포 감성카페 전포 크리스마스는 롱드라이버스",
    "query": "부산 전포 카페",
    "fetched_at": "2026-01-28T13:08:02",
    "ok": true
  },
  "text": "부산 전포 감성카페 전포 크리스마스는 롱드라이버스\n- 요약: 찾아간 부산 전포카페 롱드라이버스 전포카페 롱브라이버스는 위치가 약간 애매한데에 있긴한데... 롱드라이버스였다 #부산카페 #전포카페 #서면카페 #부산크리스마스 #서면크리스마스 #전포크리스마스...\n- 링크: https://blog.naver.com/mini11_/224103220010\n- 키워드: 부산 전포 카페"
}