{
  "id": "naver_blog_3cef2feed4436ce255140baa7b52f3d88499628d",
  "meta": {
    "source": "naver_blog",
    "url": "https://blog.naver.com/gogody2002/223716051944",
    "title": "부산수영 조용한 카페 ‘88필립스트리트‘ 크로와상 샌드위치...",
    "query": "부산 사하 카페 조용한카페 작업하기",
    "fetched_at": "2026-01-28T13:20:41",
    "ok": true
  },
  "text": "부산수영 조용한 카페 ‘88필립스트리트‘ 크로와상 샌드위치...\n- 요약: 88 Phillip street 주소 : 부산 수영구 무학로21번길 78 1층 영업시간 : 월-금 10:00-19:00 토,일 08:00-19:00... 샌드위치도 소스나 햄이 맛이 세지 않고 조화로워서 제 입맛에 딱 수영에서 카페 조용한 카페...\n- 링크: https://blog.naver.com/gogody2002/223716051944\n- 키워드: 부산 사하 카페 조용한카페 작업하기"
}