{
  "id": "naver_blog_3eaea23b587a071b50771b14297f5c022a41b9c3",
  "meta": {
    "source": "naver_blog",
    "url": "https://blog.naver.com/bsfund2019/224018509121",
    "title": "부산 전포·영도·중구 카페 탐방기｜커피 맛집 &amp; 베이커리 추천",
    "query": "부산 전포 카페",
    "fetched_at": "2026-01-28T13:09:11",
    "ok": true
  },
  "text": "부산 전포·영도·중구 카페 탐방기｜커피 맛집 &amp; 베이커리 추천\n- 요약: 카페한디 (전포 카페 맛집) 부산시 부산진구 전포대로132번길 11 운영시간 : 매일 (10:00 - 17:30) / 매달 첫주 일요일 정기 휴 전포에서 수제쿠키 맛집으로 유명한 곳입니다. 정말 다양한 쿠키들이 준비되어 있고...\n- 링크: https://blog.naver.com/bsfund2019/224018509121\n- 키워드: 부산 전포 카페"
}