{
  "id": "naver_blog_3f4f03acc59e18683912f6072f214ed31de522ee",
  "meta": {
    "source": "naver_blog",
    "url": "https://blog.naver.com/pjjim/223822934439",
    "title": "부산 기장 오션뷰 카페 &lt; 팜트리 &gt; 기장 대형 베이커리 카페",
    "query": "부산 사하 카페 대형카페 베이커리",
    "fetched_at": "2026-01-28T13:21:26",
    "ok": true
  },
  "text": "부산 기장 오션뷰 카페 &lt; 팜트리 &gt; 기장 대형 베이커리 카페\n- 요약: 가족과 연인과 단체모임으로 와서 오션뷰를 즐길 수 있는 팜트리 추천! #부산기장카페 #부산오션뷰카페 #기장카페 #기장대형카페 #기장베이커리카페 #기장카페추천 #기장가볼만한곳 #기장오션뷰카페\n- 링크: https://blog.naver.com/pjjim/223822934439\n- 키워드: 부산 사하 카페 대형카페 베이커리"
}