{
  "id": "naver_blog_41b652d549ab75aaeede69ee2e6e2dd566ffdcff",
  "meta": {
    "source": "naver_blog",
    "url": "https://blog.naver.com/fillinggood_/223358667718",
    "title": "부산 구서동 카페* ‘세모커피’ 핸드드립전문 조용하고...",
    "query": "부산 구서동 카페 조용한카페 작업하기",
    "fetched_at": "2026-01-28T13:20:51",
    "ok": true
  },
  "text": "부산 구서동 카페* ‘세모커피’ 핸드드립전문 조용하고...\n- 요약: 10:00 - 19:00 운영 18:30 라스트오더 부산 금정구 금강로445번길 16 1층 ☎️ Tel. 0507-1337-2033 #세모커피 #구서역카페 #구서동카페 #분위기좋은카페 #조용한카페 #핸드드립카페...\n- 링크: https://blog.naver.com/fillinggood_/223358667718\n- 키워드: 부산 구서동 카페 조용한카페 작업하기"
}