{
  "id": "naver_blog_4487eea7ef013aada7910f930c3b514d66bde2b0",
  "meta": {
    "source": "naver_blog",
    "url": "https://blog.naver.com/cleanscreen/223548853285",
    "title": "부산 사하 을숙도 대형카페 블랙업커피 을숙도점 내돈내산 후기",
    "query": "부산 사하 카페 대형카페 베이커리",
    "fetched_at": "2026-01-28T13:21:21",
    "ok": true
  },
  "text": "부산 사하 을숙도 대형카페 블랙업커피 을숙도점 내돈내산 후기\n- 요약: 아울리는 베이커리류가 즐비한 곳이라 뭘 먹을지 엄청 고민됩니다. 저희는 스콘 하나와 갈릭크로와상, 시오빵을 하나씩 트레이에 담고 주문하러 갑니다. 부산 사하 을숙도 대형카페 블랙업커피 을숙도점 의...\n- 링크: https://blog.naver.com/cleanscreen/223548853285\n- 키워드: 부산 사하 카페 대형카페 베이커리"
}