{
  "id": "naver_blog_4509eaa396ef862d96b4db778b80e4b5de607a0d",
  "meta": {
    "source": "naver_blog",
    "url": "https://blog.naver.com/shinhomotors/221219763346",
    "title": "[동래 조용한 카페/흡연가능 테라스 커피숍] &quot;카페유별&quot; (by....",
    "query": "부산 동래 카페 조용한카페 작업하기",
    "fetched_at": "2026-01-28T13:21:51",
    "ok": true
  },
  "text": "[동래 조용한 카페/흡연가능 테라스 커피숍] &quot;카페유별&quot; (by....\n- 요약: [동래 조용한 카페/흡연가능 테라스 커피숍] &quot;카페유별&quot; (by.신호정비) 부산 자동차 외형복원 덴트 도색 전문 신호정비 입니다 &quot; &quot; &quot; &quot; 오늘 소개할 곳은 동래역 근처에 카페입니다 그랜드 오픈한 신상가게 입니다...\n- 링크: https://blog.naver.com/shinhomotors/221219763346\n- 키워드: 부산 동래 카페 조용한카페 작업하기"
}