{
  "id": "naver_blog_4c4e23cae407bf102883942a03bc6a94c6223634",
  "meta": {
    "source": "naver_blog",
    "url": "https://blog.naver.com/jjallang-/224056157732",
    "title": "부산 광안리 베이커리카페 홍익당 민락수변공원 빵집 맛집",
    "query": "부산 광안리 베이커리 카페",
    "fetched_at": "2026-01-28T13:05:09",
    "ok": true
  },
  "text": "부산 광안리 베이커리카페 홍익당 민락수변공원 빵집 맛집\n- 요약: 부산 광안리 베이커리카페 홍익당 민락수변공원 빵집 맛집 부산 광안리의 잔잔한 바다를 배경으로... 감성 베이커리카페다. 부산 광안리를 찾는다면, 한 번쯤 들러 커피 한 잔과 함께 여유로운 시간을 보내보길...\n- 링크: https://blog.naver.com/jjallang-/224056157732\n- 키워드: 부산 광안리 베이커리 카페"
}