{
  "id": "naver_blog_57ccfaa19a347b6310fbe074b37f1a48f86c9e33",
  "meta": {
    "source": "naver_blog",
    "url": "https://blog.naver.com/yellowtory/223613164398",
    "title": "부산 광안리카페이플 광안리 디저트카페",
    "query": "부산 광안리 디저트 카페",
    "fetched_at": "2026-01-28T13:04:32",
    "ok": true
  },
  "text": "부산 광안리카페이플 광안리 디저트카페\n- 요약: ' 부산 광안리 디저트카페 분위기좋은 이플 ' #부산광안리카페 #광안리디저트카페 #광안리신상카페 광안리 새로생긴 신상 디저트카페 부산 광안리카페이플에 다녀왔어요. 바닷가 뒤편 주택가라인에 생긴...\n- 링크: https://blog.naver.com/yellowtory/223613164398\n- 키워드: 부산 광안리 디저트 카페"
}