{
  "id": "naver_blog_6a01fd74e32e9b2eaae10b295849d59263575c00",
  "meta": {
    "source": "naver_blog",
    "url": "https://blog.naver.com/xm323/224075461327",
    "title": "부산 서면 카페 추천 블랙업커피 서면본점에서 여유로운 커피...",
    "query": "부산 서면 카페",
    "fetched_at": "2026-01-28T13:10:20",
    "ok": true
  },
  "text": "부산 서면 카페 추천 블랙업커피 서면본점에서 여유로운 커피...\n- 요약: 오늘은 부산 서면에 위치한 블랙업커피 서면본점에 다녀온 후기를 공유해 드릴게요. 1층부터 4층까지... #서면카페 #부산서면카페 #서면블랙업커피 #블랙업커피 #블랙업커피서면 #서면카페추천 #서면커피...\n- 링크: https://blog.naver.com/xm323/224075461327\n- 키워드: 부산 서면 카페"
}