{
  "id": "naver_blog_6af21d30c4d2f14d0b82411681feb92f19f94891",
  "meta": {
    "source": "naver_blog",
    "url": "https://blog.naver.com/yoyokz123/222916888688",
    "title": "부산 명지 카페 바이비니 귀여운 비주얼 디저트",
    "query": "부산 명지 카페 감성카페 디저트",
    "fetched_at": "2026-01-28T13:20:28",
    "ok": true
  },
  "text": "부산 명지 카페 바이비니 귀여운 비주얼 디저트\n- 요약: 싶어서 디저트카페 알아보다가 찾아가 본 부산 명지에 있는 바이비니, 항상 카페는 누가 가자고... 그리고 소품들로 아기자기하게 예쁘게 꾸며놨던 공간 어딜 찍어도 감성샷이라며ㅎㅎ 사진찍을 맛이 났던...\n- 링크: https://blog.naver.com/yoyokz123/222916888688\n- 키워드: 부산 명지 카페 감성카페 디저트"
}