{
  "id": "naver_blog_6b8b0a52cd99c38289287255fd55ace4bf54848d",
  "meta": {
    "source": "naver_blog",
    "url": "https://blog.naver.com/hi_record/223898510134",
    "title": "부산 서면 카페 부산 명물 간식 맛볼 수 있는 파미고츄레리아",
    "query": "부산 서면 카페",
    "fetched_at": "2026-01-28T13:10:15",
    "ok": true
  },
  "text": "부산 서면 카페 부산 명물 간식 맛볼 수 있는 파미고츄레리아\n- 요약: 부산 명물 간식이라고 해도 무색할 정도로 맛도리 서면 카페,,! 부산진구 전포대로 209번길 39-3 ✔️매일 12:00 - 21:00 ✔️라스트오더 20:30 0507 1484 8667 부산 서면 카페 맛집 파미고츄레리아! 부산 명물 간식으로도...\n- 링크: https://blog.naver.com/hi_record/223898510134\n- 키워드: 부산 서면 카페"
}