{
  "id": "naver_blog_6cffa3ac0ac98b4e1a3b562c23d21133a54e16f2",
  "meta": {
    "source": "naver_blog",
    "url": "https://blog.naver.com/dwg970608/223856957778",
    "title": "애견 동반이 가능한 카페 광안리 오션뷰 카페 비엔나커피...",
    "query": "부산 구서동 카페 뷰카페 오션뷰",
    "fetched_at": "2026-01-28T13:21:06",
    "ok": true
  },
  "text": "애견 동반이 가능한 카페 광안리 오션뷰 카페 비엔나커피...\n- 요약: 광안리 뷰카페는 전면 폴딩도어를 통해 펼쳐지는 환상적인 오션뷰가 매력적인 장소입니다. 이곳은... 0507-1351-9326 #광안리한옥카페 #광안리가볼만한곳 #광안리오션뷰카페 #부산광안리카페 #광안리카페추천\n- 링크: https://blog.naver.com/dwg970608/223856957778\n- 키워드: 부산 구서동 카페 뷰카페 오션뷰"
}