{
  "id": "naver_blog_74449c29346174ce2758e546c22216478cebcf8e",
  "meta": {
    "source": "naver_blog",
    "url": "https://blog.naver.com/dlawldi/223541027866",
    "title": "광안리찻집, 광안대교가 보이는 고즈넉한 뷰카페 다혜랑",
    "query": "부산 구서동 카페 뷰카페 오션뷰",
    "fetched_at": "2026-01-28T13:21:03",
    "ok": true
  },
  "text": "광안리찻집, 광안대교가 보이는 고즈넉한 뷰카페 다혜랑\n- 요약: 광안리오션뷰카페, 다혜랑 공영주차장에 주차 가능해요 부산 광안리 민락수변공원 공영주차장 앞 건물 8층에 위치한 광안리찻집 다혜랑 방문했어요 위치: 부산 수영구 광안해변로344번길 17-3 801호 &lt;영업시간...\n- 링크: https://blog.naver.com/dlawldi/223541027866\n- 키워드: 부산 구서동 카페 뷰카페 오션뷰"
}