{
  "id": "naver_blog_79d3b365dd4fc924eec29d245123861bcc4aafc4",
  "meta": {
    "source": "naver_blog",
    "url": "https://blog.naver.com/ksyun0908/222595930336",
    "title": "[부산/ 다대포 디저트] 카페 마치 ( CAFE MARCH )",
    "query": "부산 다대포 카페 감성카페 디저트",
    "fetched_at": "2026-01-28T13:20:11",
    "ok": true
  },
  "text": "[부산/ 다대포 디저트] 카페 마치 ( CAFE MARCH )\n- 요약: #부산푸딩맛집 #다대포디저트맛집 #부산디저트맛집 #부산다대포디저트카페 #카페마치푸딩 디저트를 선물받았읍니다!!! #카페마치 카페 마치 ( CAFE MARCH ) &quot;Take out&quot; 가능합니다 ☕️ Coffee &amp; Dessert &amp; Sandwich - Mon...\n- 링크: https://blog.naver.com/ksyun0908/222595930336\n- 키워드: 부산 다대포 카페 감성카페 디저트"
}