{
  "id": "naver_blog_7cd43dfccc16a60ca9c53c08a87000b78b26a149",
  "meta": {
    "source": "naver_blog",
    "url": "https://blog.naver.com/hiddasik/224103874042",
    "title": "[ 부산 광안리 디저트카페 ] 두바이쫀득쿠키와 다양한 쿠키맛집...",
    "query": "부산 광안리 디저트 카페",
    "fetched_at": "2026-01-28T13:04:23",
    "ok": true
  },
  "text": "[ 부산 광안리 디저트카페 ] 두바이쫀득쿠키와 다양한 쿠키맛집...\n- 요약: #두바이쫀득쿠키 #두바이초콜릿 #부산디저트카페 #부산카페 #부산빵지순례 #부산디저트맛집 #부산두바이쫀득쿠키 #광안리두바이쫀득쿠키 #광안리디저트카페 #광안리카페 #광안리쿠키 #해운대카페...\n- 링크: https://blog.naver.com/hiddasik/224103874042\n- 키워드: 부산 광안리 디저트 카페"
}