{
  "id": "naver_blog_7f7620921258addf29de08bcb499590ae6e77930",
  "meta": {
    "source": "naver_blog",
    "url": "https://blog.naver.com/seoro_season/224069683628",
    "title": "부산 해리단길 베이커리 카페 밀창고",
    "query": "부산 해리단길 카페 대형카페 베이커리",
    "fetched_at": "2026-01-28T13:20:22",
    "ok": true
  },
  "text": "부산 해리단길 베이커리 카페 밀창고\n- 요약: 밀창고 이름부터 베이커리 느낌이 물씬 크리스마스 느낌도 낭낭 귀여운 쿠키인형이 달린 트리가 미리... 테이크아웃 역시 빵은 길빵 #밀창고 #밀창고부산 #부산밀창고 #해운대밀창고 #해운대빵집 #해운대빵집맛집\n- 링크: https://blog.naver.com/seoro_season/224069683628\n- 키워드: 부산 해리단길 카페 대형카페 베이커리"
}