{
  "id": "naver_blog_80cba100c3eba84fb23e91e88d863c99f2f28484",
  "meta": {
    "source": "naver_blog",
    "url": "https://blog.naver.com/zzanyou_1031/224064451440",
    "title": "[부산 센텀 근처 카페... 근처 카페] 블루보틀 부산 민락 카페",
    "query": "부산 민락 카페",
    "fetched_at": "2026-01-28T13:17:56",
    "ok": true
  },
  "text": "[부산 센텀 근처 카페... 근처 카페] 블루보틀 부산 민락 카페\n- 요약: 블루보틀 부산 민락 카페' 리뷰 들어 ~~갑니다! ♧ 1층 테이크 아웃 1층은 테이크 아웃 손님을 위한 카운터가 마련되어 있구요. 매장 이용의 경우 4층에서 주문 하면돼요! ♧ 4층 카페 블루보틀 부산 민락의 핵심...\n- 링크: https://blog.naver.com/zzanyou_1031/224064451440\n- 키워드: 부산 민락 카페"
}