{
  "id": "naver_blog_80f8b8309b5034342b9a97648cec48018b543dc4",
  "meta": {
    "source": "naver_blog",
    "url": "https://blog.naver.com/ljh6971/223927792000",
    "title": "부산 전포 카페 휘낭시에가 이렇게나 많은 혹시",
    "query": "부산 전포 카페",
    "fetched_at": "2026-01-28T13:08:28",
    "ok": true
  },
  "text": "부산 전포 카페 휘낭시에가 이렇게나 많은 혹시\n- 요약: 부산 전포동을 구경하다 잠깐 쉴 겸 해서 카페를 알아봤는데 이름이 정말 특이한 곳이 있는... 혹시 카페입니다 윌리엄 : HOXY??? 부산 전포 카페 혹시 (HOXY) 대충 보면 편집샵같기도 한 부산 전포 카페예요 이...\n- 링크: https://blog.naver.com/ljh6971/223927792000\n- 키워드: 부산 전포 카페"
}