{
  "id": "naver_blog_83489fc1764c501d4fe7a9a2ff1817dba5fe3e22",
  "meta": {
    "source": "naver_blog",
    "url": "https://blog.naver.com/oongeee/223931976222",
    "title": "[부산 망미/수영] 도심속... 좋은 조용한 힐링공간 ‘북카페...",
    "query": "부산 망미단길 카페 조용한카페 작업하기",
    "fetched_at": "2026-01-28T13:22:21",
    "ok": true
  },
  "text": "[부산 망미/수영] 도심속... 좋은 조용한 힐링공간 ‘북카페...\n- 요약: 방문했는데 힐링하기에 아주 좋은 공간이었다. 재방문의사 완전 있음 #부산 #부산카페 #부산북카페 #망미단길 #망미단길카페 #망미단길카페거리 #북키페바사크라 #바사크라 #도심속힐링공간 #카페바사크라\n- 링크: https://blog.naver.com/oongeee/223931976222\n- 키워드: 부산 망미단길 카페 조용한카페 작업하기"
}