{
  "id": "naver_blog_880b35a8698d404d56267f43c4675bd889fae1de",
  "meta": {
    "source": "naver_blog",
    "url": "https://blog.naver.com/unsoul20/223505526405",
    "title": "부산 광안리 디저트 카페 일본감성 산도를 파는 우사기 (usagi)",
    "query": "부산 광안리 디저트 카페",
    "fetched_at": "2026-01-28T13:04:30",
    "ok": true
  },
  "text": "부산 광안리 디저트 카페 일본감성 산도를 파는 우사기 (usagi)\n- 요약: 케어존 디저트 예약 가능 - 1인 3개 가능, 포장예약은 웨이팅과 무관하게 픽업 가능 (테이블 예약X) 광안리에서 제일 가보고 싶었던 카페 우사기 이렇게 핫할줄 모르고 갔는데,,다들 좋은곳은 알아보시는지...\n- 링크: https://blog.naver.com/unsoul20/223505526405\n- 키워드: 부산 광안리 디저트 카페"
}