{
  "id": "naver_blog_89410aa980191a43d6bf54016a552462a91f3261",
  "meta": {
    "source": "naver_blog",
    "url": "https://blog.naver.com/herbandal_/224146577783",
    "title": "카페오 부산 북구 화명동 베이커리 디저트 대형카페 주차장",
    "query": "부산 태종대 카페 대형카페 베이커리",
    "fetched_at": "2026-01-28T13:19:34",
    "ok": true
  },
  "text": "카페오 부산 북구 화명동 베이커리 디저트 대형카페 주차장\n- 요약: 카페오 : 외부 및 내부 모습 부산 부산 카페 부산 카페 추천 부산 대형 카페 부산 베이커리 카페 부산 주차 편한 카페 부산 예쁜 카페 부산 감성 카페 화명동 카페 화명동 카페 추천 화명동 대형 카페...\n- 링크: https://blog.naver.com/herbandal_/224146577783\n- 키워드: 부산 태종대 카페 대형카페 베이커리"
}