{
  "id": "naver_blog_89a50336730ff34317d58490d0769c384bc0ec75",
  "meta": {
    "source": "naver_blog",
    "url": "https://blog.naver.com/yumzzoni/223697666632",
    "title": "부산 남포동 대형카페 굿올데이즈 내돈내산",
    "query": "부산 남포동 카페",
    "fetched_at": "2026-01-28T13:11:54",
    "ok": true
  },
  "text": "부산 남포동 대형카페 굿올데이즈 내돈내산\n- 요약: 안녕하세요 , 죠니예요 오늘은 부산 남포동카페 크리스마스 트리가 있는 #굿올데이즈 다녀온 후기입니다! 남포동 크리스마스트리가 있는 대형카페 굿올데이즈 위치 : 부산 중구 중앙대로 41번길 5...\n- 링크: https://blog.naver.com/yumzzoni/223697666632\n- 키워드: 부산 남포동 카페"
}