{
  "id": "naver_blog_89d9440ea08f02174ed0fc543394273d0fbc59a0",
  "meta": {
    "source": "naver_blog",
    "url": "https://blog.naver.com/ttpttl2002/223699490579",
    "title": "부산 서면 핫플 데이트 코스 전포동 카페거리 이재모피자",
    "query": "부산 서면 카페",
    "fetched_at": "2026-01-28T13:12:37",
    "ok": true
  },
  "text": "부산 서면 핫플 데이트 코스 전포동 카페거리 이재모피자\n- 요약: 여전히 맛있는 피자를 맛볼 수 있어 좋았던 부산 서면 핫플 이재모피자. 부산 전포 카페거리도 바로 옆에 있어 서면 데이트 코스를 고민 중이라면 한번 방문해 보시길 바란다. ⓒ 최도령.\n- 링크: https://blog.naver.com/ttpttl2002/223699490579\n- 키워드: 부산 서면 카페"
}