{
  "id": "naver_blog_92a6d5519663580d1f1f27aa625df35c98d6fd49",
  "meta": {
    "source": "naver_blog",
    "url": "https://blog.naver.com/rkdudme/223397638784",
    "title": "부산 광안리디저트 카페 베이크꼼마 후기입니다",
    "query": "부산 광안리 디저트 카페",
    "fetched_at": "2026-01-28T13:05:06",
    "ok": true
  },
  "text": "부산 광안리디저트 카페 베이크꼼마 후기입니다\n- 요약: 오늘은 광안역 근처 광안리디저트 광안리구움과자 베이크꼼마에 다녀왔어요ㅎ 베이크꼼마 부산... 여기가 소품샵이야~ 카페야~ 잠깐 보는데도 구경할게 너무 많아서 보다가 디저트 고르는걸 깜빡함 ㅋ...\n- 링크: https://blog.naver.com/rkdudme/223397638784\n- 키워드: 부산 광안리 디저트 카페"
}