{
  "id": "naver_blog_92ceac62ae2662287831556eff905e6d1547d72b",
  "meta": {
    "source": "naver_blog",
    "url": "https://blog.naver.com/straight11111/223746119197",
    "title": "안양 금정역 호계동 조용한 카페 기버(Giver) 분위기 좋은...",
    "query": "부산 금정 카페 조용한카페 작업하기",
    "fetched_at": "2026-01-28T13:19:59",
    "ok": true
  },
  "text": "안양 금정역 호계동 조용한 카페 기버(Giver) 분위기 좋은...\n- 요약: ✔ 금정역 근처 조용한 분위기의 카페 ✔ 공부, 작업하기 좋은 분위기 (콘센트 O) ✔ 전체적으로 커피 맛과 디저트들의 퀄리티 좋음 ✔ 좌석 간격 넓은 편이라 혼자 방문해도 부담 X 이번 글은 금정역 카페...\n- 링크: https://blog.naver.com/straight11111/223746119197\n- 키워드: 부산 금정 카페 조용한카페 작업하기"
}