{
  "id": "naver_blog_9412bc3b66a53e9a3512160e493f544656647799",
  "meta": {
    "source": "naver_blog",
    "url": "https://blog.naver.com/upup7349/224158520359",
    "title": "부산 청사포 카페 오션브리즈 10개월 아기랑(주차+메뉴)",
    "query": "부산 청사포 카페 뷰카페 오션뷰",
    "fetched_at": "2026-01-28T13:21:43",
    "ok": true
  },
  "text": "부산 청사포 카페 오션브리즈 10개월 아기랑(주차+메뉴)\n- 요약: 초록초록한 인테리어에 오션뷰까지 크으 너무 좋다 ㅜㅜㅜ... 멍하니 앉아서 물멍하고 싶던 부산 청사포 카페 오션브리즈 10개월 아기의 뷰 감상 ㅋㅋㅋㅋㅋㅋㅋㅋ 사색중이니.. 제발 자줘! 하면서 야외 테라스를...\n- 링크: https://blog.naver.com/upup7349/224158520359\n- 키워드: 부산 청사포 카페 뷰카페 오션뷰"
}