{
  "id": "naver_blog_964110c1d386ba6142b568c08137bd1b2629990e",
  "meta": {
    "source": "naver_blog",
    "url": "https://blog.naver.com/giveyouwooju/223277039319",
    "title": "[동래카페] 아늑하고 조용한 허그인 부산 공간대여 주차가능",
    "query": "부산 동래 카페 조용한카페 작업하기",
    "fetched_at": "2026-01-28T13:21:50",
    "ok": true
  },
  "text": "[동래카페] 아늑하고 조용한 허그인 부산 공간대여 주차가능\n- 요약: 오랜만에 만난 친구라 조용한 곳에서 편하게 이야기를 나누고 싶어서 코지하지만 크고 조용하지만 이쁜 동래카페인 허그인 부산으로 갔어요 허그인 부산 건물에 주차장이 있어요 동래에 주차가능한 카페 잘...\n- 링크: https://blog.naver.com/giveyouwooju/223277039319\n- 키워드: 부산 동래 카페 조용한카페 작업하기"
}