{
  "id": "naver_blog_99d402798b54bd50aa3fa9e7785cdd5e1fb5e630",
  "meta": {
    "source": "naver_blog",
    "url": "https://blog.naver.com/yoonjung_e/223235299244",
    "title": "부산아이랑카페 / 괴정 &quot;카페시온(zion)&quot; 모래놀이...",
    "query": "부산 괴정 카페",
    "fetched_at": "2026-01-28T13:17:48",
    "ok": true
  },
  "text": "부산아이랑카페 / 괴정 &quot;카페시온(zion)&quot; 모래놀이...\n- 요약: 부산아이랑카페, 괴정 카페시온에 다녀왔어요 ♥ 친정집과 멀지않은 곳이라, 주말에 도전해봤어요. (너무 높고, 너무 사람 많음 주의 ㅋㅋ) 부산 괴정 카페시온 부산모래놀이카페, 토끼카페, 잔디밭카페...\n- 링크: https://blog.naver.com/yoonjung_e/223235299244\n- 키워드: 부산 괴정 카페"
}