{
  "id": "naver_blog_9c422f8bab6142170b65c65f6e57825bf4138603",
  "meta": {
    "source": "naver_blog",
    "url": "https://blog.naver.com/diva_michee/223411704528",
    "title": "부산 광안리 카페 오션뷰 테마카페 루프탑 캠핑 젊은이의 둥지",
    "query": "부산 구서동 카페 뷰카페 오션뷰",
    "fetched_at": "2026-01-28T13:21:02",
    "ok": true
  },
  "text": "부산 광안리 카페 오션뷰 테마카페 루프탑 캠핑 젊은이의 둥지\n- 요약: 대박 오션뷰 테마카페를 찾았어요 ㅎㅎ 저 부산에서 뷰 카페 맛집 만 찾아다니는거 다들 이제 익숙하시죠?ㅋㅋ 저희 찐친 언니들 중 한명과 광안리에서 핫플투어 하기로 만난 날! 핫한 부산 광안리 카페...\n- 링크: https://blog.naver.com/diva_michee/223411704528\n- 키워드: 부산 구서동 카페 뷰카페 오션뷰"
}