{
  "id": "naver_blog_9ffe67013d9b103f80c6ff8f94b21fe3ac2c62cb",
  "meta": {
    "source": "naver_blog",
    "url": "https://blog.naver.com/0109213/224115911777",
    "title": "[부산 전포동 카페] 평범하지 않은 못난이 채소의 매력에 빠지다...",
    "query": "부산 전포 카페",
    "fetched_at": "2026-01-28T13:09:12",
    "ok": true
  },
  "text": "[부산 전포동 카페] 평범하지 않은 못난이 채소의 매력에 빠지다...\n- 요약: 부산 부산진구 동성로87번길 26 1층 전포소방서 큰도로 맞은편 골목 (희와제과 근처) 영업시간 매일 10:00... 전포카페 몬나니는 밝은 햇살이 들어오는 창가에 앉아 디저트를 바라보며, 소소한 일상의 순간을...\n- 링크: https://blog.naver.com/0109213/224115911777\n- 키워드: 부산 전포 카페"
}