{
  "id": "naver_blog_a58d545cd21288c8c5ddc0d272117fc418207abc",
  "meta": {
    "source": "naver_blog",
    "url": "https://blog.naver.com/login97/224101479679",
    "title": "[부산/광안리] 광안리 대형카페 벤베커 부산광안리점 부산유일...",
    "query": "부산 광안리 카페",
    "fetched_at": "2026-01-28T12:57:38",
    "ok": true
  },
  "text": "[부산/광안리] 광안리 대형카페 벤베커 부산광안리점 부산유일...\n- 요약: 한다 광안리 아기랑 가기 좋은 카페 찾을때 완전 추천하는 광안리 대형카페 벤베커 부산광안리점 ❤️ #부산광안리카페 #부산광안리대형카페 #광안리카페 #광안리브레첼 #광안리벤버커 #벤버커광안리점\n- 링크: https://blog.naver.com/login97/224101479679\n- 키워드: 부산 광안리 카페"
}