{
  "id": "naver_blog_a6e343b766304f115ead414d0b704da8897fed8a",
  "meta": {
    "source": "naver_blog",
    "url": "https://blog.naver.com/pjjim/223528569087",
    "title": "광안리 카페 &lt; 스크러피 광안리 &gt; 부산 광안리 디저트 맛집",
    "query": "부산 광안리 카페",
    "fetched_at": "2026-01-28T12:57:55",
    "ok": true
  },
  "text": "광안리 카페 &lt; 스크러피 광안리 &gt; 부산 광안리 디저트 맛집\n- 요약: 뜨거운 여름 광안리에서 오늘도 행복하고 맛있게~~~ (오늘도 말이 좀 많은 하울이었습니다.) #광안리카페 #스크러피광안리 #광안리스크러피 #남천동카페 #광안리디저트 #부산광안리맛집 #부산광안리카페...\n- 링크: https://blog.naver.com/pjjim/223528569087\n- 키워드: 부산 광안리 카페"
}