{
  "id": "naver_blog_ac1b5f4769ff1d354b74405db5e242386ae25f90",
  "meta": {
    "source": "naver_blog",
    "url": "https://blog.naver.com/ddungmom6/222107144865",
    "title": "부산 기장 오션뷰 카페 Sea&amp;Tree &quot;씨앤트리&quot; 수영장/키즈존...",
    "query": "부산 구서동 카페 뷰카페 오션뷰",
    "fetched_at": "2026-01-28T13:21:04",
    "ok": true
  },
  "text": "부산 기장 오션뷰 카페 Sea&amp;Tree &quot;씨앤트리&quot; 수영장/키즈존...\n- 요약: 곳 부산 기장 뷰카페 #씨앤트리 맨 마지막은 루프탑인데 우와~ 정말 좋더라구요 아이때문에 후다닥 사진만 찍었는데 요즘 바다뷰 카페 많이들 생기고 있지만 부산 기장 &quot;씨앤트리&quot; 여기가 바다뷰 제...\n- 링크: https://blog.naver.com/ddungmom6/222107144865\n- 키워드: 부산 구서동 카페 뷰카페 오션뷰"
}