{
  "id": "naver_blog_af21eb06e6cc2810ce911375c1fb7a237a27c4fb",
  "meta": {
    "source": "naver_blog",
    "url": "https://blog.naver.com/majorica98/223695316633",
    "title": "부산 사상 카페 고양이가 있는 우디브룩 크리스마스트리카페...",
    "query": "부산 사상 카페",
    "fetched_at": "2026-01-28T13:17:30",
    "ok": true
  },
  "text": "부산 사상 카페 고양이가 있는 우디브룩 크리스마스트리카페...\n- 요약: 낮에 오면 냥이들 구경 많이 했을텐데 아쉬워요ㅠㅠ 부산 숲속 카페나 크리스마스 트리 구경하실 분들 고양이, 강아지 구경하고 싶으신 분들 사상 우디브룩 추천입니다 乃 #사상카페 #부산카페추천...\n- 링크: https://blog.naver.com/majorica98/223695316633\n- 키워드: 부산 사상 카페"
}