{
  "id": "naver_blog_afa67e6c9284c77763a1b11683ddac184ae91ab5",
  "meta": {
    "source": "naver_blog",
    "url": "https://blog.naver.com/nosa1015/224098050010",
    "title": "부산 전포카페 므므",
    "query": "부산 전포 카페",
    "fetched_at": "2026-01-28T13:08:01",
    "ok": true
  },
  "text": "부산 전포카페 므므\n- 요약: 부산 전포 카페 므므 #전포동카페 #전포카페 #므므 주소 | 부산 부산진구 전포동 215 ⏱️ 영업시간 | 12:00 ~ 21:00 ️ 휴무 | 정기휴무 없음 주차 | 주차불가 노키즈존, 강아지 있음 부산 전포동에 깜찍강쥐가 있는...\n- 링크: https://blog.naver.com/nosa1015/224098050010\n- 키워드: 부산 전포 카페"
}