{
  "id": "naver_blog_b0b4841737c6fe76af1debf6f3c48528b40fefc6",
  "meta": {
    "source": "naver_blog",
    "url": "https://blog.naver.com/may_13_/224150305158",
    "title": "부산 해운대 카페 로우앤스윗 로스터리 구움과자 라떼맛집",
    "query": "부산 해운대 카페",
    "fetched_at": "2026-01-28T13:10:01",
    "ok": true
  },
  "text": "부산 해운대 카페 로우앤스윗 로스터리 구움과자 라떼맛집\n- 요약: 주소 부산 해운대구 우동1로 20번길 19 전화번호 0507-1355-7328 영업시간 매일 9:00-19:00 기타 해운대역 4번출구 인근 로스터리, 핸드드립, 포장, 반려동물 O 부산 해운대 카페 로우앤스윗 로스터리 ‘외관’ 오랜만에...\n- 링크: https://blog.naver.com/may_13_/224150305158\n- 키워드: 부산 해운대 카페"
}