{
  "id": "naver_blog_b1830f569660aa5ef75800317c469db68209b4ae",
  "meta": {
    "source": "naver_blog",
    "url": "https://blog.naver.com/foreversuna/223360503881",
    "title": "부산 광안리카페 케이크맛집 조용한카페 커메인",
    "query": "부산 광안리 카페",
    "fetched_at": "2026-01-28T13:04:19",
    "ok": true
  },
  "text": "부산 광안리카페 케이크맛집 조용한카페 커메인\n- 요약: &lt;&lt;&lt; 커메인 &gt;&gt;&gt; 주소 부산 수영구 광안로35번길 17 리치하우스 1층 연락처 0507-1405-7873 영업시간 11:00 - 22... 광안리카페 커메인은 광안리해수욕장과 지하철역 중간쯤에 위치해 있어 접근성이 좋고 찾기도 쉽다....\n- 링크: https://blog.naver.com/foreversuna/223360503881\n- 키워드: 부산 광안리 카페"
}