{
  "id": "naver_blog_b2fb4f09d9fbc3f57aebaf65c0c002ed552acf11",
  "meta": {
    "source": "naver_blog",
    "url": "https://blog.naver.com/nailaaa120/223724102119",
    "title": "부산 다대포 오션뷰카페 쀼베이크",
    "query": "부산 다대포 카페 감성카페 디저트",
    "fetched_at": "2026-01-28T13:20:13",
    "ok": true
  },
  "text": "부산 다대포 오션뷰카페 쀼베이크\n- 요약: 고르고 골라 다녀온 감성카페 쀼베이크 소개해 드릴게요:) 부산 다대포 카페 쀼베이크 쀼베이크 부산... 보통 요런 느낌 카페는 디저트도 맛집이잖앙 손님이 많아서 매장 사진은 다 못 찍었지만! 매장도...\n- 링크: https://blog.naver.com/nailaaa120/223724102119\n- 키워드: 부산 다대포 카페 감성카페 디저트"
}