{
  "id": "naver_blog_b4d1aa20c7f2b81937e89ad74d86be9385a96928",
  "meta": {
    "source": "naver_blog",
    "url": "https://blog.naver.com/muraeel/224111083877",
    "title": "부산 명지 카페진목 l 노을이 예쁜 낙동강 뷰 감성카페 주차...",
    "query": "부산 명지 카페 감성카페 디저트",
    "fetched_at": "2026-01-28T13:20:29",
    "ok": true
  },
  "text": "부산 명지 카페진목 l 노을이 예쁜 낙동강 뷰 감성카페 주차...\n- 요약: 이용) 부산 명지 카페 / 명지 드라이브 코스 / 명지 감성 카페 찾는 분들께 좋아요 카페 가는 길부터... 이미 감성 터졌어요 내려서봐도 환상적이라 한참 보다가 들어갔어요 디저트 &amp; 베이커리 &amp; 음료 맛있어...\n- 링크: https://blog.naver.com/muraeel/224111083877\n- 키워드: 부산 명지 카페 감성카페 디저트"
}