{
  "id": "naver_blog_b4f17e38ca367eb336c714e6d357b77189b6ac17",
  "meta": {
    "source": "naver_blog",
    "url": "https://blog.naver.com/skswonly/224118443239",
    "title": "부산 해운대 카페, 안집",
    "query": "부산 해운대 카페",
    "fetched_at": "2026-01-28T13:12:05",
    "ok": true
  },
  "text": "부산 해운대 카페, 안집\n- 요약: 부산 해운대 카페 &lt;안집&gt; 친구들과 연말 송년회 해운대 암소갈비 가기로 한 날 웨이팅 걸어놓고 혼자 기다리며 가본 카페 안집 후기입니다. 여기가 암소갈비 사장님이 살던 주택을 개조한 공간이라고 합니다....\n- 링크: https://blog.naver.com/skswonly/224118443239\n- 키워드: 부산 해운대 카페"
}