{
  "id": "naver_blog_b69cc97e5d82a2a6493a56e77a6646afd6bba06e",
  "meta": {
    "source": "naver_blog",
    "url": "https://blog.naver.com/woosso82/223670708492",
    "title": "블루보틀 부산민락카페 웨이팅 상황 주차장 정보",
    "query": "부산 민락 카페",
    "fetched_at": "2026-01-28T13:17:51",
    "ok": true
  },
  "text": "블루보틀 부산민락카페 웨이팅 상황 주차장 정보\n- 요약: 4층 영업시간 : 09:00 - 21:00 ✔️ 민락역 1번 출구에서 594m, 신세계백화점에서 도보로 13분 블루보틀 부산 민락 카페 웨이팅 현황 캐치 테이블은 상황에 따라 오픈 블루보틀 부산 미락 카페 웨이팅은 지금...\n- 링크: https://blog.naver.com/woosso82/223670708492\n- 키워드: 부산 민락 카페"
}