{
  "id": "naver_blog_b8bbf21827522b579cf2542547d4f47b5d11bfca",
  "meta": {
    "source": "naver_blog",
    "url": "https://blog.naver.com/hhhlllmmmeee/223688403207",
    "title": "부산가볼만한곳 핸드드립맛집 온천장카페 모모스커피",
    "query": "부산 온천장 카페 조용한카페 작업하기",
    "fetched_at": "2026-01-28T13:21:35",
    "ok": true
  },
  "text": "부산가볼만한곳 핸드드립맛집 온천장카페 모모스커피\n- 요약: 바로바로 부산 온천장카페 모모스커피 본점 본점 포함 해운대 마린시티점 수영구 도모헌점 영도... 그리는 작업하시는 분들도 계시고.. 그냥 앉아만 있어도 힐링 그 자체.. ☕️리뷰 주문과 동시에 디저트 먼저...\n- 링크: https://blog.naver.com/hhhlllmmmeee/223688403207\n- 키워드: 부산 온천장 카페 조용한카페 작업하기"
}