{
  "id": "naver_blog_ba7589dbb04da58c81f135c591f1a21d050f2a96",
  "meta": {
    "source": "naver_blog",
    "url": "https://blog.naver.com/bbodung1230/224159621414",
    "title": "#부산서면 분위기 깡패 카페 원탑 &quot;넉아웃&quot; 서면점 내돈내산...",
    "query": "부산 서면 카페",
    "fetched_at": "2026-01-28T13:08:37",
    "ok": true
  },
  "text": "#부산서면 분위기 깡패 카페 원탑 &quot;넉아웃&quot; 서면점 내돈내산...\n- 요약: 부산 서면 카페 찾으신다면 꼭 &quot;넉.아.웃&quot; 빅추천! 조금은 우연히 가게 된 카페였지만 인테리어, 커피, 디저트 전부 내 취향이여서 다음에 서면에 방문하게 되면 첫 번째로 재방문 할 카페! 재방문 ×1000000% 부산...\n- 링크: https://blog.naver.com/bbodung1230/224159621414\n- 키워드: 부산 서면 카페"
}