{
  "id": "naver_blog_bbdf23dba0cabe9f7bf413642a446702ccfabf42",
  "meta": {
    "source": "naver_blog",
    "url": "https://blog.naver.com/61dmlcndjr/223438272662",
    "title": "오토바이 렌트 현지 흥정, 띠엔해변 수영, 드라이브+뷰카페 등)",
    "query": "부산 구서동 카페 뷰카페 오션뷰",
    "fetched_at": "2026-01-28T13:21:04",
    "ok": true
  },
  "text": "오토바이 렌트 현지 흥정, 띠엔해변 수영, 드라이브+뷰카페 등)\n- 요약: 급으로 들어감) 2층에 자리잡아 바라본 뷰ㅎㅎ 어딜가나 오션뷰라 다 좋음ㅎㅎ 여기는 약간 광안리? 부산? 이런 느낌이었어요 코란섬 떠나기 전 우연히 찾은 카페에서 패션후르츠 주스와 이름 모를 열대주스 한...\n- 링크: https://blog.naver.com/61dmlcndjr/223438272662\n- 키워드: 부산 구서동 카페 뷰카페 오션뷰"
}