{
  "id": "naver_blog_c35d51f3ca05d90f07b5c5aebc3e6b8e4c73f530",
  "meta": {
    "source": "naver_blog",
    "url": "https://blog.naver.com/vivace8687/224093003201",
    "title": "부산 전포 카페 디저트 맛집 힙피 크리스마스 갬성 카페",
    "query": "부산 전포 카페",
    "fetched_at": "2026-01-28T13:09:12",
    "ok": true
  },
  "text": "부산 전포 카페 디저트 맛집 힙피 크리스마스 갬성 카페\n- 요약: 절정 카페 Heap.p에 다녀왔습니다 힙피 위치:부산 부산진구 동성로25번길 12 1층 영업시간:월~금 12:00 - 22... 볼까나 #부산전포카페디저트 #전포역맛집카페 #전포대형카페케이크 #전포카페힙피 #힙피...\n- 링크: https://blog.naver.com/vivace8687/224093003201\n- 키워드: 부산 전포 카페"
}