{
  "id": "naver_blog_c41ff881eb9d0a61d8ef948ca2ed8f86d8d74159",
  "meta": {
    "source": "naver_blog",
    "url": "https://blog.naver.com/yoojh2510/224128757780",
    "title": "부산 광안리 감성 카페 듀플릿 광안점",
    "query": "부산 광안리 카페",
    "fetched_at": "2026-01-28T12:57:54",
    "ok": true
  },
  "text": "부산 광안리 감성 카페 듀플릿 광안점\n- 요약: 1층 듀플릿마켓도 있어서 구경을 하다 동생이 선물로 청개구리 가방걸이를 사주었어요 ㅎㅎ 그러고 보니 동생 닮은 청개구리~~ #광안리브런치카페 #부산광안리감성카페 #듀플릿 #듀플릿광안점 #광안리듀플릿\n- 링크: https://blog.naver.com/yoojh2510/224128757780\n- 키워드: 부산 광안리 카페"
}