{
  "id": "naver_blog_c5680a4808b1e445cd82617803b611f263668129",
  "meta": {
    "source": "naver_blog",
    "url": "https://blog.naver.com/yellowtory/224144114513",
    "title": "부산 명지 대형카페 브런치 맛집 카페 록산",
    "query": "부산 명지 카페 대형카페 베이커리",
    "fetched_at": "2026-01-28T13:19:03",
    "ok": true
  },
  "text": "부산 명지 대형카페 브런치 맛집 카페 록산\n- 요약: 명지에서 가까운 몇 안 되는 부산 명지 대형카페이자 브런치와 베이커리를 함께 즐길 수 있는 곳이라 오랜만에 생각나서 다시 방문했어요. 채광도 좋고 공간이 넓어서 여유롭게 브런치 즐기기 좋아서 명지...\n- 링크: https://blog.naver.com/yellowtory/224144114513\n- 키워드: 부산 명지 카페 대형카페 베이커리"
}