{
  "id": "naver_blog_c64ce7591a38381f6d82ad619ce1561af10f1565",
  "meta": {
    "source": "naver_blog",
    "url": "https://blog.naver.com/mihhhhh/224044890321",
    "title": "청사포카페 리베르타 청사포점, 부산 오션뷰 카페 방문 후기",
    "query": "부산 청사포 카페 뷰카페 오션뷰",
    "fetched_at": "2026-01-28T13:21:38",
    "ok": true
  },
  "text": "청사포카페 리베르타 청사포점, 부산 오션뷰 카페 방문 후기\n- 요약: 청사포카페 리베르타 청사포점, 부산 오션뷰 카페 방문 후기 가을 하늘이 너무 예뻤던 날, 가족과 부산으로 힐링 여행 다녀왔어요 부산 해운대에 머무르면서 청사포로 놀러 갔는데, 푸른 바다가 한눈에...\n- 링크: https://blog.naver.com/mihhhhh/224044890321\n- 키워드: 부산 청사포 카페 뷰카페 오션뷰"
}