{
  "id": "naver_blog_c8292c6dcad814528e6f48e5b8137bc659b51171",
  "meta": {
    "source": "naver_blog",
    "url": "https://blog.naver.com/0harin0/223956714237",
    "title": "[부산/광안리] 광안대교 오션뷰 카페 차선책 쑥 갸또 맛집",
    "query": "부산 구포 카페 뷰카페 오션뷰",
    "fetched_at": "2026-01-28T13:19:43",
    "ok": true
  },
  "text": "[부산/광안리] 광안대교 오션뷰 카페 차선책 쑥 갸또 맛집\n- 요약: 오션뷰 카페 중 디저트 맛집을 찾고 있었는데, 오늘은 차선책 본점 방문 리뷰입니당 ✨ 영업 시간 : 11:00-22:00 (21:30 라스트오더) 주차 불가 외부 광안리 해변가 바로 건너편으로 횡단보도 하나만 건너면 구포국...\n- 링크: https://blog.naver.com/0harin0/223956714237\n- 키워드: 부산 구포 카페 뷰카페 오션뷰"
}