{
  "id": "naver_blog_ca269003aa56845de7b5b7cbb4a75a2463e84b88",
  "meta": {
    "source": "naver_blog",
    "url": "https://blog.naver.com/2syeon/222040881558",
    "title": "부산 괴정, 해리포터 실사판?! 카페 만디",
    "query": "부산 괴정 카페",
    "fetched_at": "2026-01-28T13:17:47",
    "ok": true
  },
  "text": "부산 괴정, 해리포터 실사판?! 카페 만디\n- 요약: 찍자 부산 괴정 카페 만디 cafe mandi 벌써 다녀온 지 2달 가까이 되었구먼 명실상부한 사하구 핫플... 아주 길고 긴 정원을 구경하며 걸어가다 보면 저 멀리 괴정 카페 대문이 보인다. 카메라가 조금 흔들리긴...\n- 링크: https://blog.naver.com/2syeon/222040881558\n- 키워드: 부산 괴정 카페"
}