{
  "id": "naver_blog_ca287ffa56dfcdb99ff832cc6c838363aed18401",
  "meta": {
    "source": "naver_blog",
    "url": "https://blog.naver.com/blbl1990/223903144040",
    "title": "부산서면카페추천 블루리본 커피맛집 블랙업커피 서면본점",
    "query": "부산 서면 카페",
    "fetched_at": "2026-01-28T13:12:32",
    "ok": true
  },
  "text": "부산서면카페추천 블루리본 커피맛집 블랙업커피 서면본점\n- 요약: 블랙업커피 추천드려요:D #블랙업커피 #블랙업커피서면본점 #서면카페 #전포카페 #커피맛집 #커피강의 #커피수업 #드립커피 #디저트카페 #서면대형카페 #서면조용한카페 #서면데이트 #부산카페 #서면가볼만한곳\n- 링크: https://blog.naver.com/blbl1990/223903144040\n- 키워드: 부산 서면 카페"
}