{
  "id": "naver_blog_cd6107e3f8be9a84f4844302cdc71b408b2de1e0",
  "meta": {
    "source": "naver_blog",
    "url": "https://blog.naver.com/89y3c2pdvr2/224143240457",
    "title": "부산 해운대 카페 방문리뷰, 눈오는날의 특별한 하루",
    "query": "부산 해운대 카페",
    "fetched_at": "2026-01-28T13:12:06",
    "ok": true
  },
  "text": "부산 해운대 카페 방문리뷰, 눈오는날의 특별한 하루\n- 요약: 부산 해운대 카페 방문리뷰, 눈오는날의 특별한 하루 며칠 전 부산에 드물게 큰 눈이 내렸습니다... 가득한 해운대 카페 찾기 해운대에는 정말 다양한 콘셉트의 카페들이 많아요 그중에서도 오늘은 유난히...\n- 링크: https://blog.naver.com/89y3c2pdvr2/224143240457\n- 키워드: 부산 해운대 카페"
}