{
  "id": "naver_blog_d32fac2e125d90cb37b36304afba54b42a620e40",
  "meta": {
    "source": "naver_blog",
    "url": "https://blog.naver.com/jmin0925/223956744006",
    "title": "영도 오션뷰 베이터리 카페 메종드콘 뷰커피",
    "query": "부산 구서동 카페 뷰카페 오션뷰",
    "fetched_at": "2026-01-28T13:21:04",
    "ok": true
  },
  "text": "영도 오션뷰 베이터리 카페 메종드콘 뷰커피\n- 요약: 카페 답게 프라이드 가득한 이력들로 한쪽 벽면을 채우고 있어요 영도 시내가 훤히 보이는 뷰 빵들도... 별표별표 #부산영도카페 #영도카페 #영도카페추천 #영도오션뷰카페 #영도뷰카페 #청학동카페 #부산카페...\n- 링크: https://blog.naver.com/jmin0925/223956744006\n- 키워드: 부산 구서동 카페 뷰카페 오션뷰"
}