{
  "id": "naver_blog_d3e3be9aa2ceb1ed6dbabe377d49a9d652f96ff6",
  "meta": {
    "source": "naver_blog",
    "url": "https://blog.naver.com/ucfucugcugcigc/224109121737",
    "title": "[부산 프론트커피] 내돈내산 광안리카페: 메뉴, 주차 솔직후기",
    "query": "부산 구서동 카페 뷰카페 오션뷰",
    "fetched_at": "2026-01-28T13:21:05",
    "ok": true
  },
  "text": "[부산 프론트커피] 내돈내산 광안리카페: 메뉴, 주차 솔직후기\n- 요약: 가격대는 광안리 뷰카페 치고는 평균 수준. 자리에서 보이는 뷰가 이래요. 광안대교가 정면으로 딱... 아니고 “뷰 보면서 커피 한 잔 하고 금방 나가는” 느낌이 더 맞는 카페였어요. 총평 ✔ 광안리 오션뷰는...\n- 링크: https://blog.naver.com/ucfucugcugcigc/224109121737\n- 키워드: 부산 구서동 카페 뷰카페 오션뷰"
}