{
  "id": "naver_blog_d514553bed788a74956ac3b70d7117ed9efa84ea",
  "meta": {
    "source": "naver_blog",
    "url": "https://blog.naver.com/kkimjhyeon/221663964248",
    "title": "구서동 카페 포포즈 디저트가 맛있었던 조용한카페",
    "query": "부산 구서동 카페 조용한카페 작업하기",
    "fetched_at": "2026-01-28T13:20:51",
    "ok": true
  },
  "text": "구서동 카페 포포즈 디저트가 맛있었던 조용한카페\n- 요약: 구서동카페 포포즈는 조용한 카페이면서 테이블은 적당히 있는 편이라고 해야할까요?ㅋ 그리고... 조금은 색다른 와플을 먹을수있어서 좋았던 구서동카페 포포즈였어요~ 주소: 부산 금정구 수림로72번길 94 1층...\n- 링크: https://blog.naver.com/kkimjhyeon/221663964248\n- 키워드: 부산 구서동 카페 조용한카페 작업하기"
}