{
  "id": "naver_blog_dda2a6bcedc3c0753236f7570bc98e01778c0da4",
  "meta": {
    "source": "naver_blog",
    "url": "https://blog.naver.com/kbm0996/221013631640",
    "title": "입출력 이외의 문자열 관련 함수 Functions Related...",
    "query": "<위 문자열 그대로>",
    "fetched_at": "2026-01-28T13:00:36",
    "ok": true
  },
  "text": "입출력 이외의 문자열 관련 함수 Functions Related...\n- 요약: 때문에 위 예제의 실행결과로는 결코 문자열 &quot;equal&quot;가 출력되지 않는다. 따라서 문자열의... 변환 ※ 상기 내용은 '윤성우의 열혈 C 프로그래밍'에 있는 내용을 거의 그대로 썼습니다.\n- 링크: https://blog.naver.com/kbm0996/221013631640\n- 키워드: <위 문자열 그대로>"
}