{
  "id": "naver_blog_df35b0c898ab9a8dce9cd85b004ab3df56f3b981",
  "meta": {
    "source": "naver_blog",
    "url": "https://blog.naver.com/mini11_/224124747265",
    "title": "예스키즈, 예스펫 광안리 대형카페 벤베커 부산 광안리점",
    "query": "부산 광안리 카페",
    "fetched_at": "2026-01-28T12:57:23",
    "ok": true
  },
  "text": "예스키즈, 예스펫 광안리 대형카페 벤베커 부산 광안리점\n- 요약: 하며 집었던 루돌프 씨솔트 초코 브레첼 너무 많아서 다 찍지 못했는데 정말 다양한 브레첼들을 맛볼 수 있어서 부산여행 왔다면 꼭 들릴만한 필수코스라고 생각된다 광안리 대형카페 벤베커의 메뉴 음료 종류도...\n- 링크: https://blog.naver.com/mini11_/224124747265\n- 키워드: 부산 광안리 카페"
}