{
  "id": "naver_blog_e02de387d2d535b05f01f7591ecb35c86b16b6be",
  "meta": {
    "source": "naver_blog",
    "url": "https://blog.naver.com/dlxhfl92/223622183108",
    "title": "부산 화명동 맛집 화명 쿠우쿠우는 못참지",
    "query": "부산 화명 카페",
    "fetched_at": "2026-01-28T13:17:36",
    "ok": true
  },
  "text": "부산 화명동 맛집 화명 쿠우쿠우는 못참지\n- 요약: 작게 키즈카페도 있어서 어느 정도 먹고 나서 여기 놀라고 보냈어요 크지는 않지만 그래도 이런 공간 아이들도 꼭 가보고 싶어하고 엄마한테도 좀 편하게 먹을 수 있어서 좋았던 거 같네요 :) 부산 화명동 맛집...\n- 링크: https://blog.naver.com/dlxhfl92/223622183108\n- 키워드: 부산 화명 카페"
}