{
  "id": "naver_blog_e1399aa266fe1c2cdfed6eb9b4b0017879fdc6b3",
  "meta": {
    "source": "naver_blog",
    "url": "https://blog.naver.com/ilyfttend/224094779546",
    "title": "부산 광안리 베이커리카페 맛잘알 홍익당 빵집 빵지순례",
    "query": "부산 광안리 베이커리 카페",
    "fetched_at": "2026-01-28T13:05:07",
    "ok": true
  },
  "text": "부산 광안리 베이커리카페 맛잘알 홍익당 빵집 빵지순례\n- 요약: 부산 광안리 베이커리카페 홍익당 빵집 선선한 날씨에도 여전히 아름다운 바다를 즐길 수 있는... 전한다는 광안리 베이커리카페는 10년 넘게 키운 천연발효종으로 건강과 맛을 담은 빵을 만드는 곳이랍니다....\n- 링크: https://blog.naver.com/ilyfttend/224094779546\n- 키워드: 부산 광안리 베이커리 카페"
}