{
  "id": "naver_blog_e33ec2ff88074d7b81b07b1d1425d2958f4ec1f6",
  "meta": {
    "source": "naver_blog",
    "url": "https://blog.naver.com/gj30603/224106880682",
    "title": "서면 디저트 감성 카페 넉아웃 부산 크리스마스 실내데이트...",
    "query": "부산 서면 카페",
    "fetched_at": "2026-01-28T13:08:37",
    "ok": true
  },
  "text": "서면 디저트 감성 카페 넉아웃 부산 크리스마스 실내데이트...\n- 요약: 지금부터 소개해드릴게요 :-) 부산 서면 카페 넉아웃 ✔️주소 : 부산 부산진구 동천로 91-4 ✔️영업시간 : 평일 12시~00시 : 주말 11시~00시 : 라스트오더 23시 서면 느좋 카페 가볼만한곳으로 추천드릴만한...\n- 링크: https://blog.naver.com/gj30603/224106880682\n- 키워드: 부산 서면 카페"
}