{
  "id": "naver_blog_ee3f06c1ceede664521893e0e8ea44c6ed1d3094",
  "meta": {
    "source": "naver_blog",
    "url": "https://blog.naver.com/onlyher_sj/224162409209",
    "title": "부산 수플레 맛집 / 남포동 카페 쿠오리노 - [그녀만의 이야기]",
    "query": "부산 남포동 카페",
    "fetched_at": "2026-01-28T13:07:07",
    "ok": true
  },
  "text": "부산 수플레 맛집 / 남포동 카페 쿠오리노 - [그녀만의 이야기]\n- 요약: #부산수플레맛집 / #남포동카페 쿠오리노 계단 사진을 찍지 않았는데(살짝 보이는 계단 난간) 계단 끝에 있는 카페 쿠오리노 안으로 들어가요 쿠오리노 메뉴 오봉집에서 배불리 먹었지만 수플레를 먹으러...\n- 링크: https://blog.naver.com/onlyher_sj/224162409209\n- 키워드: 부산 남포동 카페"
}