{
  "id": "naver_blog_ef698c06c4c70735e4660e1e980d9b79443cf37c",
  "meta": {
    "source": "naver_blog",
    "url": "https://blog.naver.com/altkey123/223273631693",
    "title": "부산 장림 부네치아 카페 추천 - 커피열매 부네치아선셋전망대점",
    "query": "부산 장림 카페",
    "fetched_at": "2026-01-28T13:17:02",
    "ok": true
  },
  "text": "부산 장림 부네치아 카페 추천 - 커피열매 부네치아선셋전망대점\n- 요약: 직원분들도 친절하고 좋았습니다. 날씨 좋은 날 부산 장림 부네치아 오션뷰카페 커피열매 부네치아선셋전망대점애서 따뜻한 라떼 한잔 어떠신가요? 평점 : 3/5 ★★★☆☆ 오늘 블로그 끗!\n- 링크: https://blog.naver.com/altkey123/223273631693\n- 키워드: 부산 장림 카페"
}