{
  "id": "naver_blog_efe22adc8c71312bcde5910140bee38ee525f4f9",
  "meta": {
    "source": "naver_blog",
    "url": "https://blog.naver.com/spring7503/224022507558",
    "title": "부산 광안리 베이글 베이커리카페, 올선데이 베이글 광안점",
    "query": "부산 광안리 베이커리 카페",
    "fetched_at": "2026-01-28T13:05:15",
    "ok": true
  },
  "text": "부산 광안리 베이글 베이커리카페, 올선데이 베이글 광안점\n- 요약: 입니다. 언제쯤 다시 가볼 수 있을까. #부산가볼만한곳 #부산여행 #부산빵집 #부산빵지순례 #부산베이커리카페 #부산베이글 #광안리맛집 #광안리카페 #광안리일찍문여는카페 #광안리베이글 #광안리브런치\n- 링크: https://blog.naver.com/spring7503/224022507558\n- 키워드: 부산 광안리 베이커리 카페"
}