{
  "id": "naver_blog_fb9fa7a0005559e918d98c1271547794ee23fcda",
  "meta": {
    "source": "naver_blog",
    "url": "https://blog.naver.com/designer_jyj/224013827637",
    "title": "해운대 카페 부산 베이커리 후스후무무 주차 내돈내산 후기",
    "query": "부산 해운대 카페",
    "fetched_at": "2026-01-28T13:14:53",
    "ok": true
  },
  "text": "해운대 카페 부산 베이커리 후스후무무 주차 내돈내산 후기\n- 요약: 없는 부산 해운대 카페에요! 다른 예쁜 부산 카페들 후기 ▼ 버터 동굴 베이커리 직접 스케치, 제작한... 부산 해운대 빵지순례 맛집으로 꼭 한번 다녀오시는 걸 추천드려요! 해운대 카페 부산 베이커리...\n- 링크: https://blog.naver.com/designer_jyj/224013827637\n- 키워드: 부산 해운대 카페"
}