{
  "id": "naver_blog_ffd5bc448b310154eee86436693a0a1dd118694a",
  "meta": {
    "source": "naver_blog",
    "url": "https://blog.naver.com/jina_910223/222229991187",
    "title": "[부산/남산동] 카페 셀라스: 복합문화공간 (feat. 키뮤갤러리)",
    "query": "부산 남산동 카페",
    "fetched_at": "2026-01-28T13:17:08",
    "ok": true
  },
  "text": "[부산/남산동] 카페 셀라스: 복합문화공간 (feat. 키뮤갤러리)\n- 요약: #부산카페 #복합문화공간 #셀라스 평일에 일하다가 잠깐 틈이 나던 시간. 멀지 않은 곳에서 행복을 찾기 위해서 들렀던 남산동 카페 '셀라스' 커피도 한잔하고 싶던 날이었지만, 드라이브를 하고 싶던 범어사...\n- 링크: https://blog.naver.com/jina_910223/222229991187\n- 키워드: 부산 남산동 카페"
}