{
  "id": "naver_blog_5b05e65b66f1b3804ba560860f15359bdb671d76",
  "meta": {
    "source": "naver_blog",
    "url": "https://blog.naver.com/fls7488/224088312736",
    "title": "부산 광안리 카페, 언더커피ㅣ내돈내산 신상카페",
    "query": "부산 광안리 카페",
    "fetched_at": "2026-01-28T13:03:04",
    "ok": true
  },
  "text": "부산 광안리 카페, 언더커피ㅣ내돈내산 신상카페\n- 요약: 0507-1375-5712 ✅메뉴판 부산 광안리 카페, 언더커피의 메뉴판이에요 시그니처 라떼로 언더플랫과 로필즈... 추천드려요 부산 광안리 신상카페 언더커피는 수플레 치즈케이크 외에도 간단하게 같이 곁들일 수...\n- 링크: https://blog.naver.com/fls7488/224088312736\n- 키워드: 부산 광안리 카페"
}