{
  "id": "naver_blog_9d9273ffd7d30944210622aa5ca2d21d1f779b39",
  "meta": {
    "source": "naver_blog",
    "url": "https://blog.naver.com/ohrr0806/224153504595",
    "title": "부산 광안리 카페 커피가 맛있는 핫플 3곳 추천",
    "query": "부산 광안리 카페",
    "fetched_at": "2026-01-28T13:03:04",
    "ok": true
  },
  "text": "부산 광안리 카페 커피가 맛있는 핫플 3곳 추천\n- 요약: 부산 광안리 카페 커피가 맛있는 핫플 3곳 추천 부산에 있는 무무지만 저 역시 데이트나 친구 만날 때는 광안리로 자주 나가게 되어요. 광안리는 핫플도 많고, 카페도 많아서 어디 갈지 고르는 매력이 있어요...\n- 링크: https://blog.naver.com/ohrr0806/224153504595\n- 키워드: 부산 광안리 카페"
}