{
  "id": "naver_blog_eb8eaad6aa55c343ca84618934774f4ded6b01e9",
  "meta": {
    "source": "naver_blog",
    "url": "https://blog.naver.com/mhjkmk/223987469866",
    "title": "부산 광안리 카페 분위기 좋은 브런치 LP바 백석 낮석",
    "query": "부산 광안리 카페",
    "fetched_at": "2026-01-28T13:03:09",
    "ok": true
  },
  "text": "부산 광안리 카페 분위기 좋은 브런치 LP바 백석 낮석\n- 요약: 광안리 최애 가게 중 하나인 곳 조만간 또 여유를 즐기러 가보겠습니다 밤의 백석이 궁금하다면 ▼ 또 다른 최애 카페는 ▼ #부산카페 #부산광안리카페 #광안리카페 #광안리브런치카페 #낮석 #백석 #광안리LP바\n- 링크: https://blog.naver.com/mhjkmk/223987469866\n- 키워드: 부산 광안리 카페"
}