{
  "id": "naver_blog_f3da175b347796c92c376ff3c2ab8a597f9b474c",
  "meta": {
    "source": "naver_blog",
    "url": "https://blog.naver.com/ley920878/224157192430",
    "title": "부산 두쫀쿠 맛집 더팬닝 엔믹스 설윤이 칭찬한 맛집",
    "query": "부산 두쫀쿠",
    "fetched_at": "2026-01-28T10:15:22",
    "ok": true
  },
  "text": "부산 두쫀쿠 맛집 더팬닝 엔믹스 설윤이 칭찬한 맛집\n- 요약: ✨부산 두쫀쿠 맛집 더팬닝✨ 아니 두쫀쿠 말만 들었지 비주얼을 봐도 내 나이 또래가 좋아할 맛은 아닌듯해서 쳐다도 안보다가 딸아이가 서울에서 부산에 왔는데 엄마 안먹어봤지 하면서 하나 사주더라고요....\n- 링크: https://blog.naver.com/ley920878/224157192430\n- 키워드: 부산 두쫀쿠"
}