{
  "id": "naver_blog_f53b959e6837a1283ddbbaa79b06e2e43e38518f",
  "meta": {
    "source": "naver_blog",
    "url": "https://blog.naver.com/ha2nabi/224152619329",
    "title": "부산 두쫀쿠 두친자 맛집 카페모먼트리 두바이쫀득쿠키",
    "query": "부산 두쫀쿠",
    "fetched_at": "2026-01-28T10:15:25",
    "ok": true
  },
  "text": "부산 두쫀쿠 두친자 맛집 카페모먼트리 두바이쫀득쿠키\n- 요약: #두바이쫀득쿠키 #부산두바이쫀득쿠키 #부산두바이쫀득쿠키맛집 #부산두쫀쿠맛집 #모먼트리부산 #모먼트리두쫀쿠 #모먼트리두바이쫀득쿠키 #부산두친자맛집 #모먼트리웨이팅 #모먼트리부산주차\n- 링크: https://blog.naver.com/ha2nabi/224152619329\n- 키워드: 부산 두쫀쿠"
}